{"35":{"housingUnits":{"total":"912445"},"vehicle":{"one":"178344","two":"346819","three":"202081","fiveOrMore":"39512","four":"81018","total":"866079","none":"18305"},"employment":{"employed":"876210","notInLaborForce":"671217","civilians":"957385","inLaborForce":"966377","armedForces":"8992","total":"1637594","unemployed":"81175"},"age":{"median":"37.2","male":"35.7","female":"38.7"},"population":{"total":"2082669"},"poverty":{"total":"2042014","below":"426814","above":"1615200"},"household":{"total":"762551"},"vacancy":{"migrantWorkers":"754","rentedNotOccupied":"4141","forRent":"24016","seasonal":"50750","soldNotOccupied":"4192","other":"52654","total":"149894","forSale":"13387"},"income":{"family":"55900","household":"45674","perCapita":"24459"},"meta":{"name":"New Mexico","placeId":null,"waterArea":"281.3821886292696","geoId":"35","divisionId":"8","stateId":"35","countyId":null,"regionId":"4","geoType":"state","year":"2016","landArea":"121311.872109176","tractId":null,"statisticalAreaId":null,"nationId":"1"},"occupancy":{"total":"912445","occupied":"762551","vacant":"149894"},"houseValue":{"lowerQuartile":"92800","upperQuartile":"250700","average":"206486","median":"161600"}}}