{"26":{"housingUnits":{"total":"4522600"},"vehicle":{"one":"843802","two":"1949000","three":"905830","fiveOrMore":"139236","none":"103106","total":"4317017","four":"343471"},"employment":{"employed":"4479502","notInLaborForce":"2894260","civilians":"5001503","inLaborForce":"5007456","armedForces":"5953","total":"7901716","unemployed":"522001"},"age":{"median":"37.7","male":"36.5","female":"38.9"},"population":{"total":"10039208"},"poverty":{"below":"1417380","total":"9800094","above":"8382714"},"household":{"total":"3860160"},"vacancy":{"seasonal":"260345","rentedNotOccupied":"19101","forRent":"106711","soldNotOccupied":"28239","migrantWorkers":"1403","other":"154442","total":"662440","forSale":"92199"},"income":{"perCapita":"25172","household":"48700","family":"60635"},"meta":{"nationId":"1","placeId":null,"geoId":"26","waterArea":"40110.553129128784","divisionId":"3","stateId":"26","countyId":null,"regionId":"2","geoType":"state","year":"2009","landArea":"56602.944394605394","tractId":null,"name":"Michigan","statisticalAreaId":null},"occupancy":{"occupied":"3860160","total":"4522600","vacant":"662440"},"houseValue":{"median":"147500","upperQuartile":"219300","average":"181946","lowerQuartile":"94300"}},"30":{"housingUnits":{"total":"435677"},"vehicle":{"one":"75991","two":"179422","three":"114437","fiveOrMore":"29059","four":"47456","total":"455485","none":"8646"},"employment":{"employed":"469812","notInLaborForce":"263048","civilians":"497469","inLaborForce":"501225","armedForces":"3756","total":"764273","unemployed":"27657"},"age":{"median":"39.0","male":"37.7","female":"40.2"},"population":{"total":"956257"},"poverty":{"total":"931923","below":"136969","above":"794954"},"household":{"total":"372947"},"vacancy":{"seasonal":"29764","rentedNotOccupied":"1384","forRent":"7309","soldNotOccupied":"1775","migrantWorkers":"283","other":"17822","total":"62730","forSale":"4393"},"income":{"perCapita":"22881","household":"43089","family":"54475"},"meta":{"name":"Montana","placeId":null,"geoId":"30","waterArea":"1493.9098819074607","divisionId":"8","stateId":"30","countyId":null,"regionId":"4","geoType":"state","year":"2009","landArea":"145546.12712926167","tractId":null,"statisticalAreaId":null,"nationId":"1"},"occupancy":{"occupied":"372947","total":"435677","vacant":"62730"},"houseValue":{"upperQuartile":"256100","median":"162100","average":"214286","lowerQuartile":"91800"}},"40":{"housingUnits":{"total":"1624039"},"vehicle":{"one":"327681","two":"707397","fiveOrMore":"55619","three":"359165","total":"1605438","four":"136832","none":"33322"},"employment":{"employed":"1645888","notInLaborForce":"1043137","civilians":"1747781","inLaborForce":"1768798","armedForces":"21017","total":"2811935","unemployed":"101893"},"age":{"female":"37.6","male":"34.2","median":"35.9"},"population":{"total":"3610073"},"poverty":{"below":"572111","total":"3490387","above":"2918276"},"household":{"total":"1405005"},"vacancy":{"seasonal":"36351","migrantWorkers":"204","soldNotOccupied":"9759","rentedNotOccupied":"8390","forRent":"46240","other":"94758","total":"219034","forSale":"23332"},"income":{"family":"52392","household":"41861","perCapita":"22561"},"meta":{"statisticalAreaId":null,"placeId":null,"geoId":"40","waterArea":"1302.9357098512392","divisionId":"7","stateId":"40","countyId":null,"regionId":"3","geoType":"state","year":"2009","landArea":"68596.03911556999","tractId":null,"name":"Oklahoma","nationId":"1"},"occupancy":{"occupied":"1405005","total":"1624039","vacant":"219034"},"houseValue":{"upperQuartile":"156900","lowerQuartile":"62000","average":"128961","median":"98800"}},"33":{"housingUnits":{"total":"592898"},"vehicle":{"one":"104649","two":"313731","three":"152781","fiveOrMore":"29740","none":"10703","total":"672950","four":"60354"},"employment":{"employed":"698733","notInLaborForce":"316420","civilians":"737846","inLaborForce":"739413","armedForces":"1567","total":"1055833","unemployed":"39113"},"age":{"median":"39.6","male":"38.6","female":"40.5"},"population":{"total":"1315419"},"poverty":{"total":"1276098","below":"98780","above":"1177318"},"household":{"total":"502201"},"vacancy":{"migrantWorkers":"14","soldNotOccupied":"2024","rentedNotOccupied":"1850","seasonal":"59966","forRent":"8610","other":"11771","total":"90697","forSale":"6462"},"income":{"family":"75552","household":"63033","perCapita":"30640"},"meta":{"name":"New Hampshire","placeId":null,"waterArea":"396.4015293804108","geoId":"33","divisionId":"1","stateId":"33","countyId":null,"regionId":"1","geoType":"state","year":"2009","landArea":"8953.482478849664","tractId":null,"statisticalAreaId":null,"nationId":"1"},"occupancy":{"occupied":"502201","total":"592898","vacant":"90697"},"houseValue":{"upperQuartile":"357000","median":"253000","average":"290600","lowerQuartile":"181000"}},"51":{"housingUnits":{"total":"3264058"},"vehicle":{"one":"709360","two":"1524689","three":"882345","fiveOrMore":"169324","total":"3732249","four":"362830","none":"97684"},"employment":{"employed":"3768930","notInLaborForce":"1986664","civilians":"3985644","inLaborForce":"4111333","armedForces":"125689","total":"6097997","unemployed":"216714"},"population":{"total":"7721730"},"age":{"female":"38.1","male":"35.3","median":"36.7"},"poverty":{"total":"7467511","below":"752446","above":"6715065"},"household":{"total":"2936634"},"vacancy":{"seasonal":"73388","soldNotOccupied":"17342","rentedNotOccupied":"24690","forRent":"68940","migrantWorkers":"656","other":"104063","total":"327424","forSale":"38345"},"income":{"perCapita":"31606","household":"60316","family":"72193"},"meta":{"statisticalAreaId":null,"placeId":null,"waterArea":"3292.884527185005","geoId":"51","divisionId":"5","stateId":"51","countyId":null,"regionId":"3","geoType":"state","year":"2009","landArea":"39481.925304342585","tractId":null,"name":"Virginia","nationId":"1"},"houseValue":{"upperQuartile":"429400","median":"247100","average":"322404","lowerQuartile":"142200"},"occupancy":{"total":"3264058","occupied":"2936634","vacant":"327424"}},"06":{"housingUnits":{"total":"13268682"},"vehicle":{"one":"3191706","two":"6427314","fiveOrMore":"811400","three":"3551738","total":"16029709","none":"565147","four":"1578453"},"employment":{"employed":"16550706","notInLaborForce":"9857519","civilians":"17961679","inLaborForce":"18100948","armedForces":"139269","total":"27958467","unemployed":"1410973"},"age":{"female":"35.7","male":"33.4","median":"34.6"},"population":{"total":"36308527"},"poverty":{"total":"35543481","below":"4694423","above":"30849058"},"household":{"total":"12187191"},"vacancy":{"migrantWorkers":"2760","seasonal":"296689","forRent":"263819","soldNotOccupied":"49125","rentedNotOccupied":"58705","other":"261978","total":"1081491","forSale":"148415"},"income":{"family":"68909","household":"60392","perCapita":"29020"},"meta":{"name":"California","placeId":null,"waterArea":"7901.145103955577","geoId":"06","divisionId":"9","stateId":"06","countyId":null,"regionId":"4","geoType":"state","year":"2009","landArea":"155793.7388620915","tractId":null,"statisticalAreaId":null,"nationId":"1"},"occupancy":{"occupied":"12187191","total":"13268682","vacant":"1081491"},"houseValue":{"median":"479200","upperQuartile":"711400","average":"539623","lowerQuartile":"307100"}},"54":{"housingUnits":{"total":"885327"},"vehicle":{"one":"152293","two":"331430","three":"161566","fiveOrMore":"17391","none":"19333","total":"735192","four":"52353"},"employment":{"employed":"760616","notInLaborForce":"653708","civilians":"815472","inLaborForce":"817360","armedForces":"1888","total":"1471068","unemployed":"54856"},"age":{"female":"41.8","male":"38.9","median":"40.4"},"population":{"total":"1811403"},"poverty":{"total":"1763346","below":"310368","above":"1452978"},"household":{"total":"746419"},"vacancy":{"seasonal":"40733","migrantWorkers":"174","forRent":"15842","soldNotOccupied":"7753","rentedNotOccupied":"4406","other":"58106","total":"138908","forSale":"11894"},"income":{"family":"47601","household":"37356","perCapita":"20891"},"meta":{"name":"West Virginia","placeId":null,"geoId":"54","waterArea":"188.81497604379177","divisionId":"5","stateId":"54","countyId":null,"regionId":"3","geoType":"state","year":"2009","landArea":"24041.220214631656","tractId":null,"statisticalAreaId":null,"nationId":"1"},"houseValue":{"upperQuartile":"155700","median":"91400","average":"125271","lowerQuartile":"53800"},"occupancy":{"total":"885327","occupied":"746419","vacant":"138908"}},"05":{"housingUnits":{"total":"1286736"},"vehicle":{"one":"254910","two":"542811","three":"264780","fiveOrMore":"35063","none":"24853","four":"91727","total":"1212836"},"employment":{"employed":"1249579","notInLaborForce":"862253","civilians":"1348581","inLaborForce":"1355844","armedForces":"7263","total":"2218097","unemployed":"99002"},"age":{"female":"38.3","male":"35.4","median":"36.9"},"population":{"total":"2838143"},"poverty":{"total":"2755680","below":"488788","above":"2266892"},"household":{"total":"1109635"},"vacancy":{"migrantWorkers":"252","rentedNotOccupied":"5343","forRent":"37381","soldNotOccupied":"11825","seasonal":"40669","other":"62491","total":"177101","forSale":"19140"},"income":{"family":"47758","household":"38542","perCapita":"20977"},"meta":{"nationId":"1","placeId":null,"geoId":"05","waterArea":"1143.9664839452912","divisionId":"7","stateId":"05","countyId":null,"regionId":"3","geoType":"state","year":"2009","landArea":"52034.552664950126","tractId":null,"name":"Arkansas","statisticalAreaId":null},"houseValue":{"upperQuartile":"161400","median":"97200","average":"132333","lowerQuartile":"58000"},"occupancy":{"occupied":"1109635","total":"1286736","vacant":"177101"}},"12":{"housingUnits":{"total":"8641264"},"vehicle":{"one":"1898072","two":"3739702","three":"1520756","fiveOrMore":"156538","four":"492401","total":"8014285","none":"223826"},"employment":{"employed":"8224422","notInLaborForce":"5686792","civilians":"8893407","inLaborForce":"8954735","armedForces":"61328","total":"14641527","unemployed":"668985"},"age":{"female":"41.2","male":"38.1","median":"39.7"},"population":{"total":"18222420"},"poverty":{"above":"15464946","total":"17811892","below":"2346946"},"household":{"total":"7076539"},"vacancy":{"seasonal":"715571","soldNotOccupied":"69414","forRent":"259738","rentedNotOccupied":"43192","migrantWorkers":"5711","other":"283748","total":"1564725","forSale":"187351"},"income":{"perCapita":"26503","household":"47450","family":"56809"},"meta":{"statisticalAreaId":null,"placeId":null,"waterArea":"12108.588876636744","geoId":"12","divisionId":"5","stateId":"12","countyId":null,"regionId":"3","geoType":"state","year":"2009","landArea":"53648.56143447911","tractId":null,"name":"Florida","nationId":"1"},"occupancy":{"occupied":"7076539","total":"8641264","vacant":"1564725"},"houseValue":{"median":"211300","upperQuartile":"340700","average":"274256","lowerQuartile":"128800"}},"02":{"housingUnits":{"total":"280186"},"vehicle":{"one":"68806","two":"129909","fiveOrMore":"12210","three":"65843","total":"315434","none":"18743","four":"24006"},"employment":{"employed":"326950","notInLaborForce":"147066","civilians":"358292","inLaborForce":"374932","armedForces":"16640","total":"521998","unemployed":"31342"},"age":{"female":"33.5","male":"32.0","median":"32.7"},"population":{"total":"683142"},"poverty":{"below":"64038","total":"666059","above":"602021"},"household":{"total":"234779"},"vacancy":{"seasonal":"22465","rentedNotOccupied":"1516","soldNotOccupied":"1101","migrantWorkers":"232","forRent":"5900","other":"11984","total":"45407","forSale":"2209"},"income":{"family":"75493","household":"64635","perCapita":"29382"},"meta":{"name":"Alaska","placeId":null,"geoId":"02","waterArea":"94780.96693793923","divisionId":"9","stateId":"02","countyId":null,"regionId":"4","geoType":"state","year":"2009","landArea":"570983.1987555746","tractId":null,"statisticalAreaId":null,"nationId":"1"},"occupancy":{"total":"280186","occupied":"234779","vacant":"45407"},"houseValue":{"upperQuartile":"310600","lowerQuartile":"150200","average":"247767","median":"221300"}},"01":{"housingUnits":{"total":"2139970"},"vehicle":{"one":"380303","two":"809304","fiveOrMore":"80954","three":"474353","four":"184529","none":"40810","total":"1961776"},"employment":{"employed":"2013755","notInLaborForce":"1437307","civilians":"2183873","inLaborForce":"2202079","armedForces":"18206","total":"3639386","unemployed":"170118"},"age":{"female":"38.7","male":"35.5","median":"37.2"},"population":{"total":"4633360"},"poverty":{"below":"757833","above":"3755076","total":"4512909"},"household":{"total":"1819441"},"vacancy":{"seasonal":"67286","migrantWorkers":"384","rentedNotOccupied":"13120","forRent":"57008","soldNotOccupied":"11458","other":"141008","total":"320529","forSale":"30265"},"income":{"perCapita":"22732","household":"41216","family":"51989"},"meta":{"statisticalAreaId":null,"placeId":null,"waterArea":"1773.4935290756807","geoId":"01","divisionId":"6","stateId":"01","countyId":null,"regionId":"3","geoType":"state","year":"2009","landArea":"50646.58330335194","tractId":null,"name":"Alabama","nationId":"1"},"occupancy":{"total":"2139970","occupied":"1819441","vacant":"320529"},"houseValue":{"upperQuartile":"184000","median":"111900","average":"152831","lowerQuartile":"65200"}},"55":{"housingUnits":{"total":"2549915"},"vehicle":{"one":"502576","two":"1277534","three":"621985","fiveOrMore":"97770","four":"221431","none":"68972","total":"2784811"},"employment":{"employed":"2873396","notInLaborForce":"1374681","civilians":"3060803","inLaborForce":"3065789","armedForces":"4986","total":"4440470","unemployed":"187407"},"age":{"median":"37.8","male":"36.7","female":"39.0"},"population":{"total":"5599420"},"poverty":{"total":"5440780","below":"605566","above":"4835214"},"household":{"total":"2246512"},"vacancy":{"seasonal":"153146","soldNotOccupied":"7414","rentedNotOccupied":"14989","forRent":"47279","migrantWorkers":"256","other":"53807","total":"303403","forSale":"26512"},"income":{"perCapita":"26447","household":"51569","family":"64609"},"meta":{"name":"Wisconsin","placeId":null,"waterArea":"11330.149216245227","geoId":"55","divisionId":"3","stateId":"55","countyId":null,"regionId":"2","geoType":"state","year":"2009","landArea":"54166.28715980867","tractId":null,"statisticalAreaId":null,"nationId":"1"},"occupancy":{"total":"2549915","occupied":"2246512","vacant":"303403"},"houseValue":{"upperQuartile":"239600","lowerQuartile":"113600","average":"202742","median":"166100"}},"27":{"housingUnits":{"total":"2301307"},"vehicle":{"one":"459430","two":"1202469","three":"602623","fiveOrMore":"97293","four":"220526","total":"2637098","none":"62715"},"employment":{"employed":"2730225","notInLaborForce":"1174294","civilians":"2898263","inLaborForce":"2901801","armedForces":"3538","total":"4076095","unemployed":"168038"},"population":{"total":"5188581"},"age":{"median":"37.0","male":"35.9","female":"38.0"},"poverty":{"below":"506233","above":"4550723","total":"5056956"},"household":{"total":"2061882"},"vacancy":{"seasonal":"111630","rentedNotOccupied":"7583","soldNotOccupied":"8909","forRent":"38236","migrantWorkers":"423","other":"45890","total":"239425","forSale":"26754"},"income":{"perCapita":"29431","household":"57007","family":"70887"},"meta":{"nationId":"1","placeId":null,"geoId":"27","waterArea":"7314.789250830022","divisionId":"4","stateId":"27","countyId":null,"regionId":"2","geoType":"state","year":"2009","landArea":"79625.43867589893","tractId":null,"statisticalAreaId":null,"name":"Minnesota"},"houseValue":{"upperQuartile":"296500","lowerQuartile":"139500","average":"246694","median":"207000"},"occupancy":{"occupied":"2061882","total":"2301307","vacant":"239425"}},"38":{"housingUnits":{"total":"309043"},"vehicle":{"one":"54775","two":"136718","fiveOrMore":"19770","three":"80267","total":"331678","four":"35844","none":"5516"},"employment":{"employed":"339790","notInLaborForce":"155388","civilians":"352386","inLaborForce":"358902","armedForces":"6516","total":"514290","unemployed":"12596"},"age":{"female":"38.5","male":"34.8","median":"36.6"},"population":{"total":"639725"},"poverty":{"below":"75114","above":"538026","total":"613140"},"household":{"total":"273035"},"vacancy":{"seasonal":"12166","soldNotOccupied":"3262","forRent":"6654","rentedNotOccupied":"1488","migrantWorkers":"149","other":"9821","total":"36008","forSale":"2468"},"income":{"perCapita":"24978","household":"45140","family":"60381"},"meta":{"nationId":"1","placeId":null,"waterArea":"1700.1111049463339","geoId":"38","divisionId":"4","stateId":"38","countyId":null,"regionId":"2","geoType":"state","year":"2009","landArea":"68999.36494005765","tractId":null,"name":"North Dakota","statisticalAreaId":null},"occupancy":{"occupied":"273035","total":"309043","vacant":"36008"},"houseValue":{"lowerQuartile":"58100","upperQuartile":"161300","average":"126325","median":"104300"}},"46":{"housingUnits":{"total":"356404"},"vehicle":{"one":"62114","two":"164721","three":"101103","fiveOrMore":"24452","four":"45293","total":"399294","none":"6515"},"employment":{"employed":"411984","notInLaborForce":"189104","civilians":"431193","inLaborForce":"434294","armedForces":"3101","total":"623398","unemployed":"19209"},"population":{"total":"796513"},"age":{"female":"38.4","male":"35.5","median":"37.0"},"poverty":{"below":"103752","total":"767143","above":"663391"},"household":{"total":"314674"},"vacancy":{"migrantWorkers":"44","rentedNotOccupied":"1575","soldNotOccupied":"1232","forRent":"6674","seasonal":"13774","other":"15322","total":"41730","forSale":"3109"},"income":{"perCapita":"23445","household":"44828","family":"56696"},"meta":{"nationId":"1","placeId":null,"waterArea":"1306.0755806358422","geoId":"46","divisionId":"4","stateId":"46","countyId":null,"regionId":"2","geoType":"state","year":"2009","landArea":"75809.99349192264","tractId":null,"name":"South Dakota","statisticalAreaId":null},"houseValue":{"upperQuartile":"174500","median":"115400","average":"145501","lowerQuartile":"64800"},"occupancy":{"occupied":"314674","total":"356404","vacant":"41730"}},"17":{"housingUnits":{"total":"5234756"},"vehicle":{"one":"1337469","two":"2524464","three":"1164073","fiveOrMore":"165658","none":"279705","four":"436913","total":"5894584"},"employment":{"employed":"6097035","notInLaborForce":"3314242","civilians":"6624616","inLaborForce":"6644233","armedForces":"19617","total":"9958475","unemployed":"527581"},"population":{"total":"12785043"},"age":{"female":"37.2","male":"34.6","median":"35.9"},"poverty":{"below":"1549172","total":"12451259","above":"10902087"},"household":{"total":"4749388"},"vacancy":{"migrantWorkers":"1025","soldNotOccupied":"29339","seasonal":"41533","forRent":"128204","rentedNotOccupied":"20339","other":"189018","total":"485368","forSale":"75910"},"income":{"family":"67660","household":"55222","perCapita":"28469"},"meta":{"statisticalAreaId":null,"placeId":null,"waterArea":"2399.557327419597","geoId":"17","divisionId":"3","stateId":"17","countyId":null,"regionId":"2","geoType":"state","year":"2009","landArea":"55513.98752033105","tractId":null,"name":"Illinois","nationId":"1"},"occupancy":{"occupied":"4749388","total":"5234756","vacant":"485368"},"houseValue":{"upperQuartile":"328900","lowerQuartile":"114700","average":"256127","median":"200400"}},"47":{"housingUnits":{"total":"2721019"},"vehicle":{"one":"537900","two":"1161930","three":"635775","fiveOrMore":"101423","none":"54721","four":"249475","total":"2724593"},"employment":{"employed":"2809223","notInLaborForce":"1785548","civilians":"3051476","inLaborForce":"3068198","armedForces":"16722","total":"4853746","unemployed":"242253"},"age":{"median":"37.3","male":"35.9","female":"38.7"},"population":{"total":"6158953"},"poverty":{"above":"5033941","total":"6001130","below":"967189"},"household":{"total":"2412567"},"vacancy":{"migrantWorkers":"521","seasonal":"54087","forRent":"78653","rentedNotOccupied":"11899","soldNotOccupied":"15677","other":"108038","total":"308452","forSale":"39577"},"income":{"family":"52910","household":"42943","perCapita":"23557"},"meta":{"nationId":"1","placeId":null,"waterArea":"907.3877426903647","geoId":"47","divisionId":"6","stateId":"47","countyId":null,"regionId":"3","geoType":"state","year":"2009","landArea":"41236.763892182105","tractId":null,"name":"Tennessee","statisticalAreaId":null},"occupancy":{"total":"2721019","occupied":"2412567","vacant":"308452"},"houseValue":{"upperQuartile":"198100","median":"128500","average":"169705","lowerQuartile":"80800"}},"04":{"housingUnits":{"total":"2657551"},"vehicle":{"one":"629291","two":"1203954","fiveOrMore":"80349","three":"563958","total":"2741772","none":"82388","four":"204375"},"employment":{"employed":"2810448","notInLaborForce":"1795460","civilians":"3014555","inLaborForce":"3034846","armedForces":"20291","total":"4830306","unemployed":"204107"},"age":{"median":"34.8","male":"33.6","female":"36.0"},"population":{"total":"6324865"},"poverty":{"total":"6204965","below":"914040","above":"5290925"},"household":{"total":"2248170"},"vacancy":{"seasonal":"160530","soldNotOccupied":"21522","migrantWorkers":"945","forRent":"80100","rentedNotOccupied":"14922","other":"79896","total":"409381","forSale":"51466"},"income":{"perCapita":"25203","household":"50296","family":"59231"},"meta":{"statisticalAreaId":null,"placeId":null,"waterArea":"396.65726607563573","geoId":"04","divisionId":"8","stateId":"04","countyId":null,"regionId":"4","geoType":"state","year":"2009","landArea":"113590.69563795133","tractId":null,"name":"Arizona","nationId":"1"},"occupancy":{"occupied":"2248170","total":"2657551","vacant":"409381"},"houseValue":{"upperQuartile":"346100","median":"218400","average":"276491","lowerQuartile":"136100"}},"28":{"housingUnits":{"total":"1255279"},"vehicle":{"one":"242471","two":"494101","fiveOrMore":"42112","three":"275726","none":"27054","total":"1176455","four":"100923"},"employment":{"employed":"1211883","notInLaborForce":"897908","civilians":"1334527","inLaborForce":"1349864","armedForces":"15337","total":"2247772","unemployed":"122644"},"population":{"total":"2922240"},"age":{"female":"36.7","male":"33.2","median":"35.0"},"poverty":{"below":"604204","above":"2217210","total":"2821414"},"household":{"total":"1085836"},"vacancy":{"seasonal":"30781","rentedNotOccupied":"6291","soldNotOccupied":"8551","migrantWorkers":"995","forRent":"34406","other":"72454","total":"169443","forSale":"15965"},"income":{"perCapita":"19534","household":"36796","family":"45700"},"meta":{"statisticalAreaId":null,"placeId":null,"geoId":"28","waterArea":"1516.1921950078538","divisionId":"6","stateId":"28","countyId":null,"regionId":"3","geoType":"state","year":"2009","landArea":"46924.35420752673","tractId":null,"name":"Mississippi","nationId":"1"},"occupancy":{"occupied":"1085836","total":"1255279","vacant":"169443"},"houseValue":{"upperQuartile":"159100","median":"91400","average":"126452","lowerQuartile":"53700"}},"13":{"housingUnits":{"total":"3944621"},"vehicle":{"one":"925669","two":"1813944","fiveOrMore":"139439","three":"904281","four":"343518","total":"4238668","none":"134564"},"employment":{"employed":"4345885","notInLaborForce":"2477420","civilians":"4721313","inLaborForce":"4782597","armedForces":"61284","total":"7260017","unemployed":"375428"},"population":{"total":"9497667"},"age":{"female":"35.7","male":"33.1","median":"34.5"},"poverty":{"below":"1384518","total":"9228265","above":"7843747"},"household":{"total":"3417298"},"vacancy":{"seasonal":"83491","rentedNotOccupied":"19564","forRent":"140709","soldNotOccupied":"23861","migrantWorkers":"1278","other":"178371","total":"527323","forSale":"80049"},"income":{"perCapita":"25098","household":"49466","family":"58842"},"meta":{"nationId":"1","placeId":null,"waterArea":"1707.7051961785603","geoId":"13","divisionId":"5","stateId":"13","countyId":null,"regionId":"3","geoType":"state","year":"2009","landArea":"57715.341528994664","tractId":null,"name":"Georgia","statisticalAreaId":null},"occupancy":{"occupied":"3417298","total":"3944621","vacant":"527323"},"houseValue":{"upperQuartile":"247000","median":"160100","average":"210343","lowerQuartile":"101700"}},"34":{"housingUnits":{"total":"3492160"},"vehicle":{"one":"913085","two":"1707076","fiveOrMore":"118756","three":"767178","total":"4078881","four":"315217","none":"264803"},"employment":{"employed":"4217343","notInLaborForce":"2283384","civilians":"4528110","inLaborForce":"4538597","armedForces":"10487","total":"6821981","unemployed":"310767"},"population":{"total":"8650548"},"age":{"female":"39.8","male":"36.9","median":"38.3"},"poverty":{"total":"8471001","above":"7725076","below":"745925"},"household":{"total":"3152877"},"vacancy":{"seasonal":"122310","migrantWorkers":"225","rentedNotOccupied":"13603","soldNotOccupied":"13676","forRent":"75747","other":"76516","total":"339283","forSale":"37206"},"income":{"perCapita":"34566","household":"68981","family":"83957"},"meta":{"nationId":"1","placeId":null,"waterArea":"1368.6781927309298","geoId":"34","divisionId":"2","stateId":"34","countyId":null,"regionId":"1","geoType":"state","year":"2009","landArea":"7354.406726521103","tractId":null,"statisticalAreaId":null,"name":"New Jersey"},"occupancy":{"occupied":"3152877","total":"3492160","vacant":"339283"},"houseValue":{"median":"356800","upperQuartile":"499200","average":"409813","lowerQuartile":"235300"}},"29":{"housingUnits":{"total":"2648248"},"vehicle":{"one":"544182","two":"1205061","fiveOrMore":"91649","three":"598422","total":"2729556","four":"222827","none":"69419"},"employment":{"employed":"2807641","notInLaborForce":"1606756","civilians":"3016893","inLaborForce":"3034961","armedForces":"18068","total":"4641717","unemployed":"209252"},"age":{"median":"37.3","male":"35.9","female":"38.7"},"population":{"total":"5904382"},"poverty":{"total":"5732785","above":"4948507","below":"784278"},"household":{"total":"2322238"},"vacancy":{"seasonal":"72456","rentedNotOccupied":"9584","migrantWorkers":"339","forRent":"64671","soldNotOccupied":"13279","other":"124548","total":"326010","forSale":"41133"},"income":{"family":"57008","household":"46005","perCapita":"24423"},"meta":{"name":"Missouri","placeId":null,"geoId":"29","waterArea":"961.1725436498813","divisionId":"4","stateId":"29","countyId":null,"regionId":"2","geoType":"state","year":"2009","landArea":"68745.79905441198","tractId":null,"statisticalAreaId":null,"nationId":"1"},"houseValue":{"median":"134500","upperQuartile":"203100","average":"169349","lowerQuartile":"83400"},"occupancy":{"occupied":"2322238","total":"2648248","vacant":"326010"}},"23":{"housingUnits":{"total":"696948"},"vehicle":{"one":"118134","two":"295870","three":"141857","fiveOrMore":"18813","none":"12021","total":"632708","four":"45869"},"employment":{"employed":"656411","notInLaborForce":"370804","civilians":"699222","inLaborForce":"702788","armedForces":"3566","total":"1073592","unemployed":"42811"},"age":{"female":"42.5","male":"40.2","median":"41.4"},"population":{"total":"1316380"},"poverty":{"total":"1279612","below":"161582","above":"1118030"},"household":{"total":"542617"},"vacancy":{"migrantWorkers":"180","soldNotOccupied":"2453","rentedNotOccupied":"2272","seasonal":"109019","forRent":"11534","other":"20426","total":"154331","forSale":"8447"},"income":{"perCapita":"24980","household":"46541","family":"57257"},"meta":{"nationId":"1","placeId":null,"geoId":"23","waterArea":"4535.368219369699","divisionId":"1","stateId":"23","countyId":null,"regionId":"1","geoType":"state","year":"2009","landArea":"30844.707633714424","tractId":null,"name":"Maine","statisticalAreaId":null},"occupancy":{"occupied":"542617","total":"696948","vacant":"154331"},"houseValue":{"upperQuartile":"263400","median":"172100","average":"216061","lowerQuartile":"103200"}},"08":{"housingUnits":{"total":"2119839"},"vehicle":{"one":"481031","two":"1044189","fiveOrMore":"88930","three":"539084","none":"57945","total":"2399260","four":"208642"},"employment":{"employed":"2454468","notInLaborForce":"1134480","civilians":"2616764","inLaborForce":"2643932","armedForces":"27168","total":"3778412","unemployed":"162296"},"population":{"total":"4843211"},"age":{"female":"36.5","male":"34.6","median":"35.5"},"poverty":{"total":"4737172","below":"563574","above":"4173598"},"household":{"total":"1869276"},"vacancy":{"seasonal":"97367","soldNotOccupied":"7655","migrantWorkers":"896","rentedNotOccupied":"10488","forRent":"53662","other":"45498","total":"250563","forSale":"34997"},"income":{"family":"69591","household":"56222","perCapita":"29679"},"meta":{"statisticalAreaId":null,"placeId":null,"geoId":"08","waterArea":"456.22664764400486","divisionId":"8","stateId":"08","countyId":null,"regionId":"4","geoType":"state","year":"2009","landArea":"103638.65789326285","tractId":null,"name":"Colorado","nationId":"1"},"houseValue":{"upperQuartile":"355700","median":"234100","average":"294296","lowerQuartile":"166200"},"occupancy":{"occupied":"1869276","total":"2119839","vacant":"250563"}},"22":{"housingUnits":{"total":"1911254"},"vehicle":{"one":"434406","two":"843404","three":"380967","fiveOrMore":"42046","none":"61677","four":"129260","total":"1878501"},"employment":{"employed":"1936682","notInLaborForce":"1316097","civilians":"2095192","inLaborForce":"2112875","armedForces":"17683","total":"3428972","unemployed":"158510"},"population":{"total":"4411546"},"age":{"median":"35.5","male":"33.8","female":"37.1"},"poverty":{"total":"4285810","below":"789634","above":"3496176"},"household":{"total":"1644094"},"vacancy":{"seasonal":"49046","soldNotOccupied":"11242","rentedNotOccupied":"10364","migrantWorkers":"1392","forRent":"43531","other":"130729","total":"267160","forSale":"20856"},"income":{"family":"52306","household":"42167","perCapita":"22535"},"meta":{"statisticalAreaId":null,"placeId":null,"waterArea":"9171.324686988082","geoId":"22","divisionId":"7","stateId":"22","countyId":null,"regionId":"3","geoType":"state","year":"2009","landArea":"43203.902724108964","tractId":null,"name":"Louisiana","nationId":"1"},"houseValue":{"upperQuartile":"191200","median":"121300","average":"154238","lowerQuartile":"69200"},"occupancy":{"total":"1911254","occupied":"1644094","vacant":"267160"}},"56":{"housingUnits":{"total":"243133"},"vehicle":{"one":"42003","two":"100659","fiveOrMore":"20222","three":"69366","four":"32836","total":"265453","none":"3500"},"employment":{"employed":"273892","notInLaborForce":"122631","civilians":"286743","inLaborForce":"290502","armedForces":"3759","total":"413133","unemployed":"12851"},"population":{"total":"523949"},"age":{"female":"38.1","male":"35.4","median":"36.7"},"poverty":{"total":"509248","below":"49051","above":"460197"},"household":{"total":"208269"},"vacancy":{"migrantWorkers":"314","soldNotOccupied":"1256","seasonal":"15794","forRent":"4056","rentedNotOccupied":"1716","other":"8892","total":"34864","forSale":"2836"},"income":{"perCapita":"26925","household":"51990","family":"63545"},"meta":{"name":"Wyoming","placeId":null,"waterArea":"721.1117061011012","geoId":"56","divisionId":"8","stateId":"56","countyId":null,"regionId":"4","geoType":"state","year":"2009","landArea":"97088.68697040984","tractId":null,"statisticalAreaId":null,"nationId":"1"},"occupancy":{"occupied":"208269","total":"243133","vacant":"34864"},"houseValue":{"upperQuartile":"245900","lowerQuartile":"101400","average":"214264","median":"163400"}},"18":{"housingUnits":{"total":"2775849"},"vehicle":{"one":"547224","two":"1277439","three":"652893","fiveOrMore":"109674","none":"68372","total":"2900670","four":"245170"},"employment":{"employed":"3003247","notInLaborForce":"1679091","civilians":"3252608","inLaborForce":"3257604","armedForces":"4996","total":"4936695","unemployed":"249361"},"age":{"median":"36.4","male":"35.1","female":"37.8"},"population":{"total":"6342469"},"poverty":{"total":"6144219","below":"810520","above":"5333699"},"household":{"total":"2468006"},"vacancy":{"seasonal":"36046","migrantWorkers":"234","rentedNotOccupied":"14972","soldNotOccupied":"18738","forRent":"79390","other":"108064","total":"307843","forSale":"50399"},"income":{"perCapita":"24044","household":"47465","family":"58579"},"meta":{"name":"Indiana","placeId":null,"waterArea":"593.8262121295422","geoId":"18","divisionId":"3","stateId":"18","countyId":null,"regionId":"2","geoType":"state","year":"2009","landArea":"35826.15005334992","tractId":null,"statisticalAreaId":null,"nationId":"1"},"houseValue":{"upperQuartile":"174100","lowerQuartile":"81400","average":"149958","median":"120200"},"occupancy":{"occupied":"2468006","total":"2775849","vacant":"307843"}},"20":{"housingUnits":{"total":"1214929"},"vehicle":{"one":"238623","two":"585531","three":"320923","fiveOrMore":"59819","four":"129548","none":"24377","total":"1359847"},"employment":{"employed":"1392799","notInLaborForce":"669971","civilians":"1474232","inLaborForce":"1488182","armedForces":"13950","total":"2158153","unemployed":"81433"},"population":{"total":"2777835"},"age":{"median":"35.9","male":"34.5","female":"37.4"},"poverty":{"above":"2363218","below":"328843","total":"2692061"},"household":{"total":"1093694"},"vacancy":{"seasonal":"12820","rentedNotOccupied":"6211","forRent":"28257","migrantWorkers":"198","soldNotOccupied":"5618","other":"52860","total":"121235","forSale":"15271"},"income":{"family":"61181","household":"48394","perCapita":"25522"},"meta":{"statisticalAreaId":null,"placeId":null,"waterArea":"518.9758206435579","geoId":"20","divisionId":"4","stateId":"20","countyId":null,"regionId":"2","geoType":"state","year":"2009","landArea":"81759.19542560072","tractId":null,"name":"Kansas","nationId":"1"},"occupancy":{"total":"1214929","occupied":"1093694","vacant":"121235"},"houseValue":{"lowerQuartile":"69200","upperQuartile":"184700","average":"148867","median":"118500"}},"11":{"housingUnits":{"total":"283590"},"vehicle":{"one":"118080","two":"69427","three":"16810","fiveOrMore":"1822","none":"68693","four":"4396","total":"278793"},"employment":{"employed":"291830","notInLaborForce":"162849","civilians":"321466","inLaborForce":"324325","armedForces":"2859","total":"487174","unemployed":"29636"},"age":{"female":"36.2","male":"34.7","median":"35.4"},"population":{"total":"588433"},"poverty":{"below":"102142","total":"558565","above":"456423"},"household":{"total":"250723"},"vacancy":{"seasonal":"1721","migrantWorkers":"24","forRent":"8690","rentedNotOccupied":"1572","soldNotOccupied":"1988","other":"15520","total":"32867","forSale":"3352"},"income":{"family":"67006","household":"56519","perCapita":"40846"},"meta":{"statisticalAreaId":null,"placeId":null,"geoId":"11","waterArea":"7.215167485010366","divisionId":"5","stateId":"11","countyId":null,"regionId":"3","geoType":"state","year":"2009","landArea":"61.135566750404635","tractId":null,"name":"District of Columbia","nationId":"1"},"occupancy":{"occupied":"250723","total":"283590","vacant":"32867"},"houseValue":{"upperQuartile":"707500","lowerQuartile":"295800","average":"532403","median":"440500"}},"21":{"housingUnits":{"total":"1907671"},"vehicle":{"one":"347893","two":"795069","fiveOrMore":"61178","three":"412650","four":"157886","total":"1816122","none":"44732"},"employment":{"employed":"1875443","notInLaborForce":"1311122","civilians":"2029130","inLaborForce":"2046562","armedForces":"17432","total":"3357684","unemployed":"153687"},"age":{"female":"38.7","male":"35.8","median":"37.3"},"population":{"total":"4252000"},"poverty":{"below":"719746","above":"3405835","total":"4125581"},"household":{"total":"1674738"},"vacancy":{"seasonal":"32969","rentedNotOccupied":"9284","forRent":"50052","soldNotOccupied":"16654","migrantWorkers":"755","other":"94333","total":"232933","forSale":"28886"},"income":{"perCapita":"22284","household":"41197","family":"51323"},"meta":{"statisticalAreaId":null,"placeId":null,"geoId":"21","waterArea":"917.1230344856152","divisionId":"6","stateId":"21","countyId":null,"regionId":"3","geoType":"state","year":"2009","landArea":"39490.33212363006","tractId":null,"name":"Kentucky","nationId":"1"},"houseValue":{"upperQuartile":"174600","median":"113100","average":"145134","lowerQuartile":"68000"},"occupancy":{"total":"1907671","occupied":"1674738","vacant":"232933"}},"16":{"housingUnits":{"total":"626901"},"vehicle":{"one":"103417","two":"284431","fiveOrMore":"39100","three":"174797","four":"68901","total":"675489","none":"10194"},"employment":{"employed":"693052","notInLaborForce":"386049","civilians":"740053","inLaborForce":"745000","armedForces":"4947","total":"1131049","unemployed":"47001"},"age":{"female":"34.9","male":"33.2","median":"34.0"},"population":{"total":"1492573"},"poverty":{"total":"1457590","above":"1261469","below":"196121"},"household":{"total":"552726"},"vacancy":{"seasonal":"33031","migrantWorkers":"1109","forRent":"11078","soldNotOccupied":"3089","rentedNotOccupied":"2300","other":"14681","total":"74175","forSale":"8887"},"income":{"perCapita":"22262","household":"46183","family":"54057"},"meta":{"nationId":"1","placeId":null,"waterArea":"923.4492419051937","geoId":"16","divisionId":"8","stateId":"16","countyId":null,"regionId":"4","geoType":"state","year":"2009","landArea":"82645.08505184083","tractId":null,"statisticalAreaId":null,"name":"Idaho"},"occupancy":{"total":"626901","occupied":"552726","vacant":"74175"},"houseValue":{"upperQuartile":"249700","median":"166700","average":"216430","lowerQuartile":"110100"}},"25":{"housingUnits":{"total":"2727374"},"vehicle":{"one":"723503","two":"1395886","fiveOrMore":"73511","three":"576930","none":"169661","four":"220735","total":"3155355"},"employment":{"employed":"3292019","notInLaborForce":"1703438","civilians":"3528738","inLaborForce":"3535390","armedForces":"6652","total":"5238828","unemployed":"236719"},"age":{"female":"39.8","male":"37.2","median":"38.5"},"population":{"total":"6511176"},"poverty":{"above":"5649621","below":"633667","total":"6283288"},"household":{"total":"2465654"},"vacancy":{"seasonal":"104313","migrantWorkers":"121","forRent":"52515","rentedNotOccupied":"12918","soldNotOccupied":"7589","other":"62010","total":"261720","forSale":"22254"},"income":{"perCapita":"33460","household":"64496","family":"80822"},"meta":{"statisticalAreaId":null,"placeId":null,"geoId":"25","waterArea":"2752.8796204296614","divisionId":"1","stateId":"25","countyId":null,"regionId":"1","geoType":"state","year":"2009","landArea":"7801.242516769557","tractId":null,"name":"Massachusetts","nationId":"1"},"occupancy":{"total":"2727374","occupied":"2465654","vacant":"261720"},"houseValue":{"upperQuartile":"491100","lowerQuartile":"249400","average":"413380","median":"357600"}},"39":{"housingUnits":{"total":"5064437"},"vehicle":{"one":"1006549","two":"2301735","fiveOrMore":"192706","three":"1147843","four":"437546","none":"145114","total":"5240877"},"employment":{"employed":"5418915","notInLaborForce":"3180855","civilians":"5888138","inLaborForce":"5899737","armedForces":"11599","total":"9080592","unemployed":"469223"},"age":{"female":"39.4","male":"36.5","median":"37.9"},"population":{"total":"11511858"},"poverty":{"total":"11194344","below":"1526350","above":"9667994"},"household":{"total":"4526164"},"vacancy":{"seasonal":"50535","rentedNotOccupied":"21867","forRent":"152530","soldNotOccupied":"25743","migrantWorkers":"490","other":"204327","total":"538273","forSale":"82781"},"income":{"perCapita":"24830","household":"47144","family":"59208"},"meta":{"statisticalAreaId":null,"placeId":null,"geoId":"39","waterArea":"3964.8254218474203","divisionId":"3","stateId":"39","countyId":null,"regionId":"2","geoType":"state","year":"2009","landArea":"40860.75999620777","tractId":null,"name":"Ohio","nationId":"1"},"occupancy":{"occupied":"4526164","total":"5064437","vacant":"538273"},"houseValue":{"upperQuartile":"194600","lowerQuartile":"90800","average":"164413","median":"134500"}},"37":{"housingUnits":{"total":"4120599"},"vehicle":{"one":"820221","two":"1732064","three":"942393","fiveOrMore":"141532","four":"349960","total":"4070624","none":"101549"},"employment":{"employed":"4171964","notInLaborForce":"2473901","civilians":"4518581","inLaborForce":"4610855","armedForces":"92274","total":"7084756","unemployed":"346617"},"population":{"total":"9045705"},"age":{"median":"36.6","male":"35.1","female":"38.1"},"poverty":{"total":"8768580","below":"1320816","above":"7447764"},"household":{"total":"3541807"},"vacancy":{"migrantWorkers":"1689","rentedNotOccupied":"16885","soldNotOccupied":"16922","forRent":"122693","seasonal":"171981","other":"189317","total":"578792","forSale":"59305"},"income":{"perCapita":"24547","household":"45069","family":"55529"},"meta":{"nationId":"1","placeId":null,"geoId":"37","waterArea":"5199.279232768454","divisionId":"5","stateId":"37","countyId":null,"regionId":"3","geoType":"state","year":"2009","landArea":"48619.39541854275","tractId":null,"statisticalAreaId":null,"name":"North Carolina"},"houseValue":{"median":"143700","upperQuartile":"228300","average":"191243","lowerQuartile":"89000"},"occupancy":{"total":"4120599","occupied":"3541807","vacant":"578792"}},"53":{"housingUnits":{"total":"2745170"},"vehicle":{"one":"588925","two":"1243285","fiveOrMore":"155224","three":"694394","four":"287702","total":"3022299","none":"77591"},"employment":{"employed":"3089219","notInLaborForce":"1725677","civilians":"3321811","inLaborForce":"3374721","armedForces":"52910","total":"5100398","unemployed":"232592"},"population":{"total":"6465755"},"age":{"female":"37.8","male":"35.7","median":"36.8"},"poverty":{"total":"6332211","below":"749120","above":"5583091"},"household":{"total":"2512327"},"vacancy":{"migrantWorkers":"761","seasonal":"74703","forRent":"51022","soldNotOccupied":"9361","rentedNotOccupied":"11435","other":"54337","total":"232843","forSale":"31224"},"income":{"family":"68457","household":"56384","perCapita":"29320"},"meta":{"nationId":"1","placeId":null,"geoId":"53","waterArea":"4849.16467378889","divisionId":"9","stateId":"53","countyId":null,"regionId":"4","geoType":"state","year":"2009","landArea":"66453.04182499282","tractId":null,"name":"Washington","statisticalAreaId":null},"occupancy":{"total":"2745170","occupied":"2512327","vacant":"232843"},"houseValue":{"lowerQuartile":"179400","upperQuartile":"418700","average":"337409","median":"277600"}},"72":{"housingUnits":{"total":"1434711"},"vehicle":{"one":"349865","two":"470938","fiveOrMore":"19319","three":"177405","total":"1157980","none":"83586","four":"61589"},"employment":{"employed":"1208908","notInLaborForce":"1615525","civilians":"1443419","inLaborForce":"1445739","armedForces":"2320","total":"3061264","unemployed":"234511"},"population":{"total":"3940109"},"age":{"female":"37.1","male":"33.6","median":"35.3"},"poverty":{"total":"3883414","below":"1752629","above":"2130785"},"household":{"total":"1213939"},"vacancy":{"seasonal":"50568","migrantWorkers":"207","forRent":"24703","rentedNotOccupied":"3741","soldNotOccupied":"10200","other":"111798","total":"220772","forSale":"19555"},"income":{"family":"21641","household":"18627","perCapita":"10056"},"meta":{"statisticalAreaId":null,"placeId":null,"geoId":"72","waterArea":"1900.542532386312","divisionId":null,"stateId":"72","countyId":null,"regionId":null,"geoType":"state","year":"2009","landArea":"3424.2999011191255","tractId":null,"name":"Puerto Rico","nationId":"1"},"occupancy":{"occupied":"1213939","total":"1434711","vacant":"220772"},"houseValue":{"median":"107200","upperQuartile":"162200","average":"139440","lowerQuartile":"74900"}},"19":{"housingUnits":{"total":"1326723"},"vehicle":{"one":"242718","two":"648882","fiveOrMore":"66596","three":"356601","none":"29706","total":"1485064","four":"143602"},"employment":{"employed":"1545698","notInLaborForce":"725861","civilians":"1625628","inLaborForce":"1628086","armedForces":"2458","total":"2353947","unemployed":"79930"},"age":{"female":"39.3","male":"36.5","median":"37.9"},"population":{"total":"2978880"},"poverty":{"below":"326922","total":"2875698","above":"2548776"},"household":{"total":"1215970"},"vacancy":{"migrantWorkers":"183","soldNotOccupied":"6769","rentedNotOccupied":"4518","forRent":"23210","seasonal":"18647","other":"39646","total":"110753","forSale":"17780"},"income":{"perCapita":"25060","household":"48052","family":"60884"},"meta":{"name":"Iowa","placeId":null,"waterArea":"418.60455176932015","geoId":"19","divisionId":"4","stateId":"19","countyId":null,"regionId":"2","geoType":"state","year":"2009","landArea":"55854.02782418326","tractId":null,"statisticalAreaId":null,"nationId":"1"},"houseValue":{"lowerQuartile":"75500","upperQuartile":"173600","average":"143978","median":"115800"},"occupancy":{"total":"1326723","occupied":"1215970","vacant":"110753"}},"36":{"housingUnits":{"total":"7950035"},"vehicle":{"one":"2245892","two":"2856927","three":"1234518","fiveOrMore":"168355","four":"468082","total":"8758532","none":"1813156"},"employment":{"employed":"9102596","notInLaborForce":"5653927","civilians":"9790887","inLaborForce":"9816866","armedForces":"25979","total":"15470793","unemployed":"688291"},"population":{"total":"19423896"},"age":{"female":"39.1","male":"36.1","median":"37.7"},"poverty":{"below":"2615897","above":"16276765","total":"18892662"},"household":{"total":"7137013"},"vacancy":{"seasonal":"264375","soldNotOccupied":"37740","rentedNotOccupied":"41431","forRent":"159766","migrantWorkers":"911","other":"241131","total":"813022","forSale":"67668"},"income":{"perCapita":"30634","household":"55233","family":"67040"},"meta":{"name":"New York","placeId":null,"waterArea":"7431.306197297798","geoId":"36","divisionId":"2","stateId":"36","countyId":null,"regionId":"1","geoType":"state","year":"2009","landArea":"47123.44017241955","tractId":null,"statisticalAreaId":null,"nationId":"1"},"houseValue":{"upperQuartile":"520400","median":"300600","average":"371233","lowerQuartile":"121300"},"occupancy":{"occupied":"7137013","total":"7950035","vacant":"813022"}},"44":{"housingUnits":{"total":"450769"},"vehicle":{"one":"103356","two":"220426","fiveOrMore":"15592","three":"104004","none":"13962","four":"41735","total":"498376"},"employment":{"employed":"523367","notInLaborForce":"285531","civilians":"563270","inLaborForce":"566918","armedForces":"3648","total":"852449","unemployed":"39903"},"age":{"median":"38.6","male":"37.1","female":"40.2"},"population":{"total":"1057381"},"poverty":{"below":"118618","above":"900762","total":"1019380"},"household":{"total":"404227"},"vacancy":{"seasonal":"15534","soldNotOccupied":"1326","rentedNotOccupied":"1929","migrantWorkers":"0","forRent":"11528","other":"11992","total":"46542","forSale":"4233"},"income":{"family":"71037","household":"55569","perCapita":"28638"},"meta":{"statisticalAreaId":null,"placeId":null,"geoId":"44","waterArea":"511.0720322367343","divisionId":"1","stateId":"44","countyId":null,"regionId":"1","geoType":"state","year":"2009","landArea":"1033.89660027815","tractId":null,"name":"Rhode Island","nationId":"1"},"occupancy":{"total":"450769","occupied":"404227","vacant":"46542"},"houseValue":{"median":"283700","upperQuartile":"390000","average":"337626","lowerQuartile":"217500"}},"35":{"housingUnits":{"total":"862521"},"vehicle":{"one":"183075","two":"351048","three":"194873","fiveOrMore":"34691","total":"856159","none":"18377","four":"78596"},"employment":{"employed":"877146","notInLaborForce":"570096","civilians":"940644","inLaborForce":"949425","armedForces":"8781","total":"1519521","unemployed":"63498"},"population":{"total":"1964860"},"age":{"female":"37.0","male":"34.1","median":"35.5"},"poverty":{"total":"1922439","below":"347165","above":"1575274"},"household":{"total":"736630"},"vacancy":{"migrantWorkers":"523","soldNotOccupied":"4658","rentedNotOccupied":"3913","seasonal":"41706","forRent":"21377","other":"43403","total":"125891","forSale":"10311"},"income":{"family":"51205","household":"42742","perCapita":"22461"},"meta":{"statisticalAreaId":null,"placeId":null,"geoId":"35","waterArea":"281.3821886292696","divisionId":"8","stateId":"35","countyId":null,"regionId":"4","geoType":"state","year":"2009","landArea":"121311.872109176","tractId":null,"name":"New Mexico","nationId":"1"},"occupancy":{"total":"862521","occupied":"736630","vacant":"125891"},"houseValue":{"upperQuartile":"239800","median":"150500","average":"195369","lowerQuartile":"83900"}},"45":{"housingUnits":{"total":"2020422"},"vehicle":{"one":"401738","two":"828133","fiveOrMore":"59132","three":"432587","four":"158589","total":"1922576","none":"53939"},"employment":{"employed":"1971789","notInLaborForce":"1292139","civilians":"2152896","inLaborForce":"2188561","armedForces":"35665","total":"3480700","unemployed":"181107"},"population":{"total":"4416867"},"age":{"female":"38.8","male":"35.5","median":"37.2"},"poverty":{"total":"4277311","below":"676555","above":"3600756"},"household":{"total":"1693388"},"vacancy":{"migrantWorkers":"621","soldNotOccupied":"13025","forRent":"70109","rentedNotOccupied":"8582","seasonal":"101488","other":"100367","total":"327034","forSale":"32842"},"income":{"perCapita":"23196","household":"43572","family":"53707"},"meta":{"statisticalAreaId":null,"placeId":null,"geoId":"45","waterArea":"1959.5529252881915","divisionId":"5","stateId":"45","countyId":null,"regionId":"3","geoType":"state","year":"2009","landArea":"30063.81310336628","tractId":null,"name":"South Carolina","nationId":"1"},"occupancy":{"occupied":"1693388","total":"2020422","vacant":"327034"},"houseValue":{"lowerQuartile":"75100","upperQuartile":"212000","average":"180961","median":"128400"}},"32":{"housingUnits":{"total":"1089982"},"vehicle":{"one":"283426","two":"524232","fiveOrMore":"38700","three":"231921","four":"89873","none":"41178","total":"1200643"},"employment":{"employed":"1224279","notInLaborForce":"627821","civilians":"1320133","inLaborForce":"1329085","armedForces":"8952","total":"1956906","unemployed":"95854"},"population":{"total":"2545763"},"age":{"female":"35.9","male":"34.8","median":"35.3"},"poverty":{"below":"278516","total":"2509251","above":"2230735"},"household":{"total":"944178"},"vacancy":{"migrantWorkers":"383","rentedNotOccupied":"6312","soldNotOccupied":"8806","forRent":"42424","seasonal":"33145","other":"29749","total":"145804","forSale":"24985"},"income":{"family":"63912","household":"55585","perCapita":"27395"},"meta":{"name":"Nevada","placeId":null,"waterArea":"790.4306833913886","geoId":"32","divisionId":"8","stateId":"32","countyId":null,"regionId":"4","geoType":"state","year":"2009","landArea":"109780.23618690124","tractId":null,"statisticalAreaId":null,"nationId":"1"},"occupancy":{"occupied":"944178","total":"1089982","vacant":"145804"},"houseValue":{"upperQuartile":"393900","median":"275300","average":"325026","lowerQuartile":"183300"}},"50":{"housingUnits":{"total":"311617"},"vehicle":{"one":"60795","two":"150026","three":"66474","fiveOrMore":"8843","none":"5371","total":"315333","four":"22457"},"employment":{"employed":"329640","notInLaborForce":"157375","civilians":"349254","inLaborForce":"349927","armedForces":"673","total":"507302","unemployed":"19614"},"population":{"total":"620414"},"age":{"median":"40.6","male":"39.3","female":"41.7"},"poverty":{"below":"65749","above":"533310","total":"599059"},"household":{"total":"250375"},"vacancy":{"seasonal":"46373","rentedNotOccupied":"1096","soldNotOccupied":"724","forRent":"4345","migrantWorkers":"63","other":"6321","total":"61242","forSale":"2320"},"income":{"family":"63482","household":"51284","perCapita":"27036"},"meta":{"statisticalAreaId":null,"placeId":null,"waterArea":"397.8460927686059","geoId":"50","divisionId":"1","stateId":"50","countyId":null,"regionId":"1","geoType":"state","year":"2009","landArea":"9217.870865528661","tractId":null,"name":"Vermont","nationId":"1"},"occupancy":{"total":"311617","occupied":"250375","vacant":"61242"},"houseValue":{"lowerQuartile":"134200","upperQuartile":"290800","average":"242540","median":"200600"}},"10":{"housingUnits":{"total":"387801"},"vehicle":{"one":"80765","two":"183234","three":"85742","fiveOrMore":"12924","total":"402240","four":"29892","none":"11702"},"employment":{"employed":"413261","notInLaborForce":"236798","civilians":"442074","inLaborForce":"445451","armedForces":"3377","total":"682249","unemployed":"28813"},"population":{"total":"863832"},"age":{"median":"37.8","male":"36.3","female":"39.1"},"poverty":{"above":"751253","total":"839758","below":"88505"},"household":{"total":"325160"},"vacancy":{"migrantWorkers":"69","rentedNotOccupied":"1620","soldNotOccupied":"1779","forRent":"9746","seasonal":"33602","other":"9317","total":"62641","forSale":"6508"},"income":{"family":"68868","household":"57618","perCapita":"28935"},"meta":{"name":"Delaware","placeId":null,"waterArea":"540.5374806287581","geoId":"10","divisionId":"5","stateId":"10","countyId":null,"regionId":"3","geoType":"state","year":"2009","landArea":"1948.2427837923656","tractId":null,"statisticalAreaId":null,"nationId":"1"},"occupancy":{"total":"387801","occupied":"325160","vacant":"62641"},"houseValue":{"lowerQuartile":"159900","upperQuartile":"348100","average":"277728","median":"235000"}},"48":{"housingUnits":{"total":"9407692"},"vehicle":{"one":"2408636","two":"4799405","three":"2208069","fiveOrMore":"268148","none":"272468","total":"10601909","four":"777219"},"employment":{"employed":"10860964","notInLaborForce":"6139804","civilians":"11652848","inLaborForce":"11749614","armedForces":"96766","total":"17889418","unemployed":"791884"},"population":{"total":"23819042"},"age":{"female":"34.1","male":"31.9","median":"33.0"},"poverty":{"below":"3892532","above":"19315624","total":"23208156"},"household":{"total":"8269046"},"vacancy":{"migrantWorkers":"3511","rentedNotOccupied":"50383","forRent":"343072","soldNotOccupied":"45300","seasonal":"208760","other":"360031","total":"1138646","forSale":"127589"},"income":{"perCapita":"24318","household":"48199","family":"56650"},"meta":{"nationId":"1","placeId":null,"waterArea":"7338.375486904644","geoId":"48","divisionId":"7","stateId":"48","countyId":null,"regionId":"3","geoType":"state","year":"2009","landArea":"261257.250118659","tractId":null,"statisticalAreaId":null,"name":"Texas"},"occupancy":{"occupied":"8269046","total":"9407692","vacant":"1138646"},"houseValue":{"upperQuartile":"185200","lowerQuartile":"73100","average":"159065","median":"118900"}},"42":{"housingUnits":{"total":"5481676"},"vehicle":{"one":"1179735","two":"2500791","three":"1169695","fiveOrMore":"167457","total":"5683387","four":"417353","none":"265337"},"employment":{"employed":"5901533","notInLaborForce":"3715882","civilians":"6329266","inLaborForce":"6339699","armedForces":"10433","total":"10055581","unemployed":"427733"},"age":{"female":"41.0","male":"38.0","median":"39.6"},"population":{"total":"12516596"},"poverty":{"above":"10619001","total":"12081192","below":"1462191"},"household":{"total":"4893127"},"vacancy":{"migrantWorkers":"298","soldNotOccupied":"29809","rentedNotOccupied":"24800","forRent":"111155","seasonal":"160213","other":"199541","total":"588549","forSale":"62733"},"income":{"perCapita":"26678","household":"49737","family":"62520"},"meta":{"statisticalAreaId":null,"placeId":null,"geoId":"42","waterArea":"1310.6585225237975","divisionId":"2","stateId":"42","countyId":null,"regionId":"1","geoType":"state","year":"2009","landArea":"44743.233322247586","tractId":null,"name":"Pennsylvania","nationId":"1"},"occupancy":{"occupied":"4893127","total":"5481676","vacant":"588549"},"houseValue":{"median":"152300","upperQuartile":"246600","average":"199081","lowerQuartile":"87700"}},"15":{"housingUnits":{"total":"505087"},"vehicle":{"one":"134043","two":"232800","three":"124928","fiveOrMore":"45590","four":"55760","none":"21899","total":"612507"},"employment":{"employed":"605129","notInLaborForce":"343167","civilians":"636661","inLaborForce":"681035","armedForces":"44374","total":"1024202","unemployed":"31532"},"population":{"total":"1280241"},"age":{"female":"39.4","male":"35.7","median":"37.5"},"poverty":{"total":"1250787","below":"117745","above":"1133042"},"household":{"total":"437976"},"vacancy":{"seasonal":"29786","soldNotOccupied":"1936","forRent":"16345","rentedNotOccupied":"1693","migrantWorkers":"171","other":"13658","total":"67111","forSale":"3522"},"income":{"family":"74532","household":"64661","perCapita":"28662"},"meta":{"nationId":"1","placeId":null,"geoId":"15","waterArea":"4547.43748790251","divisionId":"9","stateId":"15","countyId":null,"regionId":"4","geoType":"state","year":"2009","landArea":"6422.41951955265","tractId":null,"name":"Hawaii","statisticalAreaId":null},"houseValue":{"upperQuartile":"726000","median":"521500","average":"567086","lowerQuartile":"338400"},"occupancy":{"total":"505087","occupied":"437976","vacant":"67111"}},"31":{"housingUnits":{"total":"778882"},"vehicle":{"one":"157599","two":"385411","fiveOrMore":"41040","three":"213855","none":"16652","total":"898987","four":"88534"},"employment":{"employed":"924569","notInLaborForce":"398828","civilians":"972217","inLaborForce":"978653","armedForces":"6436","total":"1377481","unemployed":"47648"},"population":{"total":"1772124"},"age":{"median":"35.9","male":"34.6","female":"37.3"},"poverty":{"below":"201851","above":"1515284","total":"1717135"},"household":{"total":"702637"},"vacancy":{"seasonal":"14598","rentedNotOccupied":"3553","forRent":"19626","soldNotOccupied":"2551","migrantWorkers":"149","other":"26129","total":"76245","forSale":"9639"},"income":{"family":"60443","household":"47995","perCapita":"24568"},"meta":{"name":"Nebraska","placeId":null,"geoId":"31","waterArea":"529.6661897961765","divisionId":"4","stateId":"31","countyId":null,"regionId":"2","geoType":"state","year":"2009","landArea":"76817.59526376927","tractId":null,"statisticalAreaId":null,"nationId":"1"},"occupancy":{"total":"778882","occupied":"702637","vacant":"76245"},"houseValue":{"median":"119700","upperQuartile":"171300","average":"144369","lowerQuartile":"78400"}},"09":{"housingUnits":{"total":"1437133"},"vehicle":{"one":"323542","two":"734330","fiveOrMore":"57901","three":"370723","none":"52133","total":"1678626","four":"145060"},"employment":{"employed":"1745261","notInLaborForce":"890540","civilians":"1873816","inLaborForce":"1880914","armedForces":"7098","total":"2771454","unemployed":"128555"},"population":{"total":"3494487"},"age":{"female":"40.4","male":"37.5","median":"39.0"},"poverty":{"below":"295608","above":"3086956","total":"3382564"},"household":{"total":"1327482"},"vacancy":{"migrantWorkers":"152","soldNotOccupied":"4336","seasonal":"23054","forRent":"30749","rentedNotOccupied":"6137","other":"33145","total":"109651","forSale":"12078"},"income":{"family":"83797","household":"67721","perCapita":"36468"},"meta":{"nationId":"1","placeId":null,"waterArea":"701.0138632604363","geoId":"09","divisionId":"1","stateId":"09","countyId":null,"regionId":"1","geoType":"state","year":"2009","landArea":"4842.6851915344105","tractId":null,"name":"Connecticut","statisticalAreaId":null},"houseValue":{"upperQuartile":"446900","median":"295800","average":"379085","lowerQuartile":"204900"},"occupancy":{"total":"1437133","occupied":"1327482","vacant":"109651"}},"49":{"housingUnits":{"total":"919334"},"vehicle":{"one":"179513","two":"493418","fiveOrMore":"84875","three":"312412","none":"21898","four":"149094","total":"1223706"},"employment":{"employed":"1251982","notInLaborForce":"582931","civilians":"1319805","inLaborForce":"1326531","armedForces":"6726","total":"1909462","unemployed":"67823"},"age":{"median":"28.5","male":"28.0","female":"29.0"},"population":{"total":"2651816"},"poverty":{"above":"2338109","total":"2610053","below":"271944"},"household":{"total":"831563"},"vacancy":{"seasonal":"37732","migrantWorkers":"99","forRent":"15357","rentedNotOccupied":"2822","soldNotOccupied":"4783","other":"17015","total":"87771","forSale":"9963"},"income":{"family":"63426","household":"55642","perCapita":"22684"},"meta":{"name":"Utah","placeId":null,"geoId":"49","waterArea":"2702.2612058204863","divisionId":"8","stateId":"49","countyId":null,"regionId":"4","geoType":"state","year":"2009","landArea":"82195.82971573614","tractId":null,"statisticalAreaId":null,"nationId":"1"},"occupancy":{"occupied":"831563","total":"919334","vacant":"87771"},"houseValue":{"lowerQuartile":"148600","upperQuartile":"305200","average":"255235","median":"208100"}},"41":{"housingUnits":{"total":"1607411"},"vehicle":{"one":"356562","two":"728364","three":"368916","fiveOrMore":"69915","four":"137225","total":"1708604","none":"53059"},"employment":{"employed":"1765814","notInLaborForce":"1045023","civilians":"1915890","inLaborForce":"1919162","armedForces":"3272","total":"2964185","unemployed":"150076"},"age":{"female":"38.8","male":"36.7","median":"37.7"},"population":{"total":"3727407"},"poverty":{"above":"3153116","total":"3649549","below":"496433"},"household":{"total":"1464196"},"vacancy":{"seasonal":"48056","rentedNotOccupied":"6341","forRent":"32641","migrantWorkers":"473","soldNotOccupied":"10290","other":"26661","total":"143215","forSale":"18753"},"income":{"perCapita":"25893","household":"49033","family":"60025"},"meta":{"nationId":"1","placeId":null,"geoId":"41","waterArea":"2390.8939621667732","divisionId":"9","stateId":"41","countyId":null,"regionId":"4","geoType":"state","year":"2009","landArea":"95987.69673162852","tractId":null,"statisticalAreaId":null,"name":"Oregon"},"houseValue":{"median":"244200","upperQuartile":"371600","average":"298897","lowerQuartile":"165500"},"occupancy":{"total":"1607411","occupied":"1464196","vacant":"143215"}},"24":{"housingUnits":{"total":"2313193"},"vehicle":{"one":"585879","two":"1147829","three":"599357","fiveOrMore":"110455","none":"123010","four":"244393","total":"2795663"},"employment":{"employed":"2866430","notInLaborForce":"1359073","civilians":"3049380","inLaborForce":"3076979","armedForces":"27599","total":"4436052","unemployed":"182950"},"age":{"median":"37.3","male":"35.8","female":"38.6"},"population":{"total":"5637418"},"poverty":{"total":"5496430","below":"449770","above":"5046660"},"household":{"total":"2092538"},"vacancy":{"migrantWorkers":"271","rentedNotOccupied":"8037","seasonal":"46411","forRent":"56762","soldNotOccupied":"8591","other":"75615","total":"220655","forSale":"24968"},"income":{"family":"83818","household":"69475","perCapita":"34236"},"meta":{"nationId":"1","placeId":null,"waterArea":"2694.980309076209","geoId":"24","divisionId":"5","stateId":"24","countyId":null,"regionId":"3","geoType":"state","year":"2009","landArea":"9710.894107960494","tractId":null,"name":"Maryland","statisticalAreaId":null},"occupancy":{"total":"2313193","occupied":"2092538","vacant":"220655"},"houseValue":{"median":"326400","upperQuartile":"476100","average":"381051","lowerQuartile":"210800"}}}